genlist_butler/__init__.py
genlist_butler/__main__.py
genlist_butler/cli.py
genlist_butler-1.2.11.dist-info/licenses/LICENSE
genlist_butler-1.2.11.dist-info/METADATA
genlist_butler-1.2.11.dist-info/WHEEL
genlist_butler-1.2.11.dist-info/entry_points.txt
genlist_butler-1.2.11.dist-info/top_level.txt
genlist_butler-1.2.11.dist-info/RECORD
