Metadata-Version: 2.4
Name: genlist-butler
Version: 1.2.11
Summary: Generate HTML catalogs from music notation files with git-based version tracking
Author-email: Tuesday Ukulele Group <tuesdayukes@gmail.com>
License: MIT
Project-URL: Homepage, https://github.com/TuesdayUkes/genlist-butler
Project-URL: Repository, https://github.com/TuesdayUkes/genlist-butler
Project-URL: Bug Tracker, https://github.com/TuesdayUkes/genlist-butler/issues
Project-URL: Documentation, https://github.com/TuesdayUkes/genlist-butler#readme
Keywords: music,catalog,chordpro,html,git,ukulele
Classifier: Development Status :: 4 - Beta
Classifier: Intended Audience :: End Users/Desktop
Classifier: License :: OSI Approved :: MIT License
Classifier: Programming Language :: Python :: 3
Classifier: Programming Language :: Python :: 3.9
Classifier: Programming Language :: Python :: 3.10
Classifier: Programming Language :: Python :: 3.11
Classifier: Programming Language :: Python :: 3.12
Classifier: Programming Language :: Python :: 3.13
Classifier: Topic :: Multimedia :: Sound/Audio
Classifier: Topic :: Text Processing :: Markup :: HTML
Requires-Python: >=3.9
License-File: LICENSE
Requires-Dist: first>=2.0.0
Provides-Extra: dev
Requires-Dist: pytest>=7.0; extra == "dev"
Requires-Dist: black>=23.0; extra == "dev"
Requires-Dist: flake8>=6.0; extra == "dev"
Requires-Dist: mypy>=1.0; extra == "dev"
Dynamic: license-file
